cursofiap/__init__.py
cursofiap/core.py
cursofiap_luisa-1.0.0.dist-info/METADATA
cursofiap_luisa-1.0.0.dist-info/WHEEL
cursofiap_luisa-1.0.0.dist-info/top_level.txt
cursofiap_luisa-1.0.0.dist-info/RECORD
